scan_camera/__init__.py
scan_camera/final_scan.py
scan_camera-0.0.5.dist-info/LICENSE
scan_camera-0.0.5.dist-info/METADATA
scan_camera-0.0.5.dist-info/WHEEL
scan_camera-0.0.5.dist-info/entry_points.txt
scan_camera-0.0.5.dist-info/top_level.txt
scan_camera-0.0.5.dist-info/RECORD
