Metadata-Version: 2.1
Name: scan-camera
Version: 0.0.5
Summary: A scanner that could scan all the ip off the world
Home-page: https://xujh.top
Author: Oliver Xu
Author-email: 273601727@qq.com
License: UNKNOWN
Platform: UNKNOWN
Classifier: Programming Language :: Python :: 2
Classifier: License :: OSI Approved :: MIT License
Classifier: Operating System :: OS Independent
Requires-Dist: requests
Requires-Dist: gevent
Requires-Dist: fire
